README.rst
setup.cfg
setup.py
minilib/Drive.py
minilib/Joystick.py
minilib/Motor.py
minilib/Servo.py
minilib/__init__.py
minilib.egg-info/PKG-INFO
minilib.egg-info/SOURCES.txt
minilib.egg-info/dependency_links.txt
minilib.egg-info/not-zip-safe
minilib.egg-info/requires.txt
minilib.egg-info/top_level.txt