Metadata-Version: 1.1
Name: minilib
Version: 0.18
Summary: Package for adafruit powered servo bots
Home-page: http://github.com/atikul99/minibot
Author: Abir
Author-email: atikul10152002@gmail.com
License: MIT
Platform: UNKNOWN
Classifier: Development Status :: 3 - Alpha
Classifier: Intended Audience :: Developers
Classifier: License :: OSI Approved :: MIT License
Classifier: Programming Language :: Python :: 3
Classifier: Programming Language :: Python :: 3.7
